[
  {
    "user_id": "27b0e2c7-9bdf-44a8-b930-8b3eba44d402",
    "datetime": "20/10/2025 09:52:31 IST",
    "event": "Punch In",
    "name": "Shubham Jadhav"
  },
  {
    "user_id": "27b0e2c7-9bdf-44a8-b930-8b3eba44d402",
    "datetime": "20/10/2025 19:00:13 IST",
    "event": "Punch Out",
    "note": "",
    "name": "Shubham Jadhav"
  },
  {
    "user_id": "e28c464b-50b3-41ad-8632-3322ce0f5eed",
    "datetime": "20/10/2025 10:59:29 IST",
    "event": "Punch In",
    "name": "Shawn Nadar"
  },
  {
    "user_id": "e28c464b-50b3-41ad-8632-3322ce0f5eed",
    "datetime": "20/10/2025 20:00:17 IST",
    "event": "Punch Out",
    "note": "",
    "name": "Shawn Nadar"
  },
  {
    "user_id": "e28c464b-50b3-41ad-8632-3322ce0f5eed",
    "datetime": "20/10/2025 18:30:39 IST",
    "event": "Break Start",
    "name": "Shawn Nadar"
  },
  {
    "user_id": "e28c464b-50b3-41ad-8632-3322ce0f5eed",
    "datetime": "20/10/2025 19:21:50 IST",
    "event": "Break End",
    "name": "Shawn Nadar"
  },
  {
    "user_id": "27b0e2c7-9bdf-44a8-b930-8b3eba44d402",
    "datetime": "21/10/2025 10:00:11 IST",
    "event": "Punch In",
    "name": "Shubham Jadhav"
  },
  {
    "user_id": "a53a173f-9a7c-4c4b-875d-7c8edb5b6b7e",
    "datetime": "21/10/2025 10:13:14 IST",
    "event": "Punch In",
    "name": "Akash Gitaye"
  },
  {
    "user_id": "5d2d7843-9744-4fb5-948b-73cc554a92dc",
    "datetime": "21/10/2025 10:17:08 IST",
    "event": "Punch In",
    "name": "Gaurav Ghadi"
  },
  {
    "user_id": "ba1c916b-8e81-48d9-8ffe-0dfc63cee87f",
    "datetime": "21/10/2025 10:30:20 IST",
    "event": "Punch In",
    "name": "Manesh Chindarkar"
  }
]
