[
  {
    "datetime": "2025-09-26T14:30:10",
    "name": "Manesh Chindarkar",
    "user_id": "ba1c916b-8e81-48d9-8ffe-0dfc63cee87f",
    "event": "Punch In"
  },
  {
    "datetime": "2025-09-29T06:31:53",
    "name": "Manesh Chindarkar",
    "user_id": "ba1c916b-8e81-48d9-8ffe-0dfc63cee87f",
    "event": "Punch Out"
  },
  {
    "datetime": "2025-09-26T14:30:25",
    "name": "Manesh Chindarkar",
    "user_id": "ba1c916b-8e81-48d9-8ffe-0dfc63cee87f",
    "event": "Break Start"
  },
  {
    "datetime": "2025-09-26T14:30:51",
    "name": "Manesh Chindarkar",
    "user_id": "ba1c916b-8e81-48d9-8ffe-0dfc63cee87f",
    "event": "Break End"
  },
  {
    "datetime": "2025-09-29T06:21:16",
    "name": "Manesh Chindarkar",
    "user_id": "ba1c916b-8e81-48d9-8ffe-0dfc63cee87f",
    "event": "Break Start"
  },
  {
    "datetime": "2025-09-29T06:22:17",
    "name": "Manesh Chindarkar",
    "user_id": "ba1c916b-8e81-48d9-8ffe-0dfc63cee87f",
    "event": "Break End"
  },
  {
    "datetime": "2025-09-29T05:28:26",
    "name": "Shawn Nadar",
    "user_id": "e28c464b-50b3-41ad-8632-3322ce0f5eed",
    "event": "Punch In"
  },
  {
    "datetime": "2025-09-29T14:31:33",
    "name": "Shawn Nadar",
    "user_id": "e28c464b-50b3-41ad-8632-3322ce0f5eed",
    "event": "Punch Out"
  },
  {
    "datetime": "2025-09-29T13:38:54",
    "name": "Shawn Nadar",
    "user_id": "e28c464b-50b3-41ad-8632-3322ce0f5eed",
    "event": "Break Start"
  },
  {
    "datetime": "2025-09-29T14:07:07",
    "name": "Shawn Nadar",
    "user_id": "e28c464b-50b3-41ad-8632-3322ce0f5eed",
    "event": "Break End"
  },
  {
    "datetime": "2025-09-29T06:19:42",
    "name": "Alizain Patel",
    "user_id": "e634f02e-1486-4ec5-9530-a92c2dc93ef8",
    "event": "Punch In"
  },
  {
    "datetime": "2025-10-06T09:08:22",
    "name": "Alizain Patel",
    "user_id": "e634f02e-1486-4ec5-9530-a92c2dc93ef8",
    "event": "Punch Out"
  },
  {
    "datetime": "2025-09-29T04:32:00",
    "name": "Akash Gitaye",
    "user_id": "a53a173f-9a7c-4c4b-875d-7c8edb5b6b7e",
    "event": "Punch In"
  },
  {
    "datetime": "2025-09-29T14:11:15",
    "name": "Akash Gitaye",
    "user_id": "a53a173f-9a7c-4c4b-875d-7c8edb5b6b7e",
    "event": "Punch Out"
  },
  {
    "datetime": "2025-09-29T08:32:10",
    "name": "Akash Gitaye",
    "user_id": "a53a173f-9a7c-4c4b-875d-7c8edb5b6b7e",
    "event": "Break Start"
  },
  {
    "datetime": "2025-09-29T09:30:48",
    "name": "Akash Gitaye",
    "user_id": "a53a173f-9a7c-4c4b-875d-7c8edb5b6b7e",
    "event": "Break End"
  },
  {
    "datetime": "2025-09-29T06:31:38",
    "name": "Shubham Jadhav",
    "user_id": "27b0e2c7-9bdf-44a8-b930-8b3eba44d402",
    "event": "Punch In"
  },
  {
    "datetime": "2025-09-29T19:06:52",
    "name": "Shubham Jadhav",
    "user_id": "27b0e2c7-9bdf-44a8-b930-8b3eba44d402",
    "event": "Punch Out"
  },
  {
    "datetime": "2025-09-29T08:31:22",
    "name": "Shubham Jadhav",
    "user_id": "27b0e2c7-9bdf-44a8-b930-8b3eba44d402",
    "event": "Break Start"
  },
  {
    "datetime": "2025-09-29T09:35:34",
    "name": "Shubham Jadhav",
    "user_id": "27b0e2c7-9bdf-44a8-b930-8b3eba44d402",
    "event": "Break End"
  },
  {
    "datetime": "2025-09-29T06:31:56",
    "name": "Manesh Chindarkar",
    "user_id": "ba1c916b-8e81-48d9-8ffe-0dfc63cee87f",
    "event": "Punch In"
  },
  {
    "datetime": "2025-09-29T14:34:52",
    "name": "Manesh Chindarkar",
    "user_id": "ba1c916b-8e81-48d9-8ffe-0dfc63cee87f",
    "event": "Punch Out"
  },
  {
    "datetime": "2025-09-29T08:29:42",
    "name": "Manesh Chindarkar",
    "user_id": "ba1c916b-8e81-48d9-8ffe-0dfc63cee87f",
    "event": "Break Start"
  },
  {
    "datetime": "2025-09-29T09:35:22",
    "name": "Manesh Chindarkar",
    "user_id": "ba1c916b-8e81-48d9-8ffe-0dfc63cee87f",
    "event": "Break End"
  },
  {
    "datetime": "2025-09-30T04:31:04",
    "name": "Shubham Jadhav",
    "user_id": "27b0e2c7-9bdf-44a8-b930-8b3eba44d402",
    "event": "Punch In"
  },
  {
    "datetime": "2025-09-30T14:30:25",
    "name": "Shubham Jadhav",
    "user_id": "27b0e2c7-9bdf-44a8-b930-8b3eba44d402",
    "event": "Punch Out"
  },
  {
    "datetime": "2025-09-30T12:39:11",
    "name": "Shubham Jadhav",
    "user_id": "27b0e2c7-9bdf-44a8-b930-8b3eba44d402",
    "event": "Break Start"
  },
  {
    "datetime": "2025-09-30T13:34:56",
    "name": "Shubham Jadhav",
    "user_id": "27b0e2c7-9bdf-44a8-b930-8b3eba44d402",
    "event": "Break End"
  },
  {
    "datetime": "2025-09-30T04:32:38",
    "name": "Akash Gitaye",
    "user_id": "a53a173f-9a7c-4c4b-875d-7c8edb5b6b7e",
    "event": "Punch In"
  },
  {
    "datetime": "2025-09-30T14:04:08",
    "name": "Akash Gitaye",
    "user_id": "a53a173f-9a7c-4c4b-875d-7c8edb5b6b7e",
    "event": "Punch Out"
  },
  {
    "datetime": "2025-09-30T08:03:29",
    "name": "Akash Gitaye",
    "user_id": "a53a173f-9a7c-4c4b-875d-7c8edb5b6b7e",
    "event": "Break Start"
  },
  {
    "datetime": "2025-09-30T09:04:17",
    "name": "Akash Gitaye",
    "user_id": "a53a173f-9a7c-4c4b-875d-7c8edb5b6b7e",
    "event": "Break End"
  },
  {
    "datetime": "2025-09-30T05:10:10",
    "name": "Shawn Nadar",
    "user_id": "e28c464b-50b3-41ad-8632-3322ce0f5eed",
    "event": "Punch In"
  },
  {
    "datetime": "2025-09-30T14:32:20",
    "name": "Shawn Nadar",
    "user_id": "e28c464b-50b3-41ad-8632-3322ce0f5eed",
    "event": "Punch Out"
  },
  {
    "datetime": "2025-09-30T09:07:23",
    "name": "Shawn Nadar",
    "user_id": "e28c464b-50b3-41ad-8632-3322ce0f5eed",
    "event": "Break Start"
  },
  {
    "datetime": "2025-09-30T09:48:42",
    "name": "Shawn Nadar",
    "user_id": "e28c464b-50b3-41ad-8632-3322ce0f5eed",
    "event": "Break End"
  },
  {
    "datetime": "2025-09-30T13:45:11",
    "name": "Shawn Nadar",
    "user_id": "e28c464b-50b3-41ad-8632-3322ce0f5eed",
    "event": "Break Start"
  },
  {
    "datetime": "2025-09-30T13:53:45",
    "name": "Shawn Nadar",
    "user_id": "e28c464b-50b3-41ad-8632-3322ce0f5eed",
    "event": "Break End"
  },
  {
    "datetime": "2025-09-30T05:25:16",
    "name": "Manesh Chindarkar",
    "user_id": "ba1c916b-8e81-48d9-8ffe-0dfc63cee87f",
    "event": "Punch In"
  },
  {
    "datetime": "2025-09-30T14:35:08",
    "name": "Manesh Chindarkar",
    "user_id": "ba1c916b-8e81-48d9-8ffe-0dfc63cee87f",
    "event": "Punch Out"
  },
  {
    "datetime": "2025-09-30T08:03:12",
    "name": "Manesh Chindarkar",
    "user_id": "ba1c916b-8e81-48d9-8ffe-0dfc63cee87f",
    "event": "Break Start"
  },
  {
    "datetime": "2025-09-30T09:08:48",
    "name": "Manesh Chindarkar",
    "user_id": "ba1c916b-8e81-48d9-8ffe-0dfc63cee87f",
    "event": "Break End"
  },
  {
    "datetime": "2025-09-30T05:49:13",
    "name": "Joshua Dsouza",
    "user_id": "7e559b4c-660d-4e63-a8b2-0c223c968ce3",
    "event": "Punch In"
  },
  {
    "datetime": "2025-09-30T14:31:10",
    "name": "Joshua Dsouza",
    "user_id": "7e559b4c-660d-4e63-a8b2-0c223c968ce3",
    "event": "Punch Out"
  },
  {
    "datetime": "2025-09-30T09:07:10",
    "name": "Joshua Dsouza",
    "user_id": "7e559b4c-660d-4e63-a8b2-0c223c968ce3",
    "event": "Break Start"
  },
  {
    "datetime": "2025-09-30T09:35:05",
    "name": "Joshua Dsouza",
    "user_id": "7e559b4c-660d-4e63-a8b2-0c223c968ce3",
    "event": "Break End"
  },
  {
    "datetime": "2025-09-30T12:59:49",
    "name": "Joshua Dsouza",
    "user_id": "7e559b4c-660d-4e63-a8b2-0c223c968ce3",
    "event": "Break Start"
  },
  {
    "datetime": "2025-09-30T13:18:22",
    "name": "Joshua Dsouza",
    "user_id": "7e559b4c-660d-4e63-a8b2-0c223c968ce3",
    "event": "Break End"
  },
  {
    "datetime": "2025-10-01T04:50:02",
    "name": "Shubham Jadhav",
    "user_id": "27b0e2c7-9bdf-44a8-b930-8b3eba44d402",
    "event": "Punch In"
  },
  {
    "datetime": "2025-10-01T14:10:55",
    "name": "Shubham Jadhav",
    "user_id": "27b0e2c7-9bdf-44a8-b930-8b3eba44d402",
    "event": "Punch Out"
  },
  {
    "datetime": "2025-10-01T08:12:34",
    "name": "Shubham Jadhav",
    "user_id": "27b0e2c7-9bdf-44a8-b930-8b3eba44d402",
    "event": "Break Start"
  },
  {
    "datetime": "2025-10-01T09:08:21",
    "name": "Shubham Jadhav",
    "user_id": "27b0e2c7-9bdf-44a8-b930-8b3eba44d402",
    "event": "Break End"
  },
  {
    "datetime": "2025-10-01T05:13:39",
    "name": "Shawn Nadar",
    "user_id": "e28c464b-50b3-41ad-8632-3322ce0f5eed",
    "event": "Punch In"
  },
  {
    "datetime": "2025-10-01T14:40:09",
    "name": "Shawn Nadar",
    "user_id": "e28c464b-50b3-41ad-8632-3322ce0f5eed",
    "event": "Punch Out"
  },
  {
    "datetime": "2025-10-01T09:11:23",
    "name": "Shawn Nadar",
    "user_id": "e28c464b-50b3-41ad-8632-3322ce0f5eed",
    "event": "Break Start"
  },
  {
    "datetime": "2025-10-01T09:50:19",
    "name": "Shawn Nadar",
    "user_id": "e28c464b-50b3-41ad-8632-3322ce0f5eed",
    "event": "Break End"
  },
  {
    "datetime": "2025-10-01T13:42:37",
    "name": "Shawn Nadar",
    "user_id": "e28c464b-50b3-41ad-8632-3322ce0f5eed",
    "event": "Break Start"
  },
  {
    "datetime": "2025-10-01T14:01:06",
    "name": "Shawn Nadar",
    "user_id": "e28c464b-50b3-41ad-8632-3322ce0f5eed",
    "event": "Break End"
  },
  {
    "datetime": "2025-10-01T05:22:37",
    "name": "Manesh Chindarkar",
    "user_id": "ba1c916b-8e81-48d9-8ffe-0dfc63cee87f",
    "event": "Punch In"
  },
  {
    "datetime": "2025-10-01T11:37:55",
    "name": "Manesh Chindarkar",
    "user_id": "ba1c916b-8e81-48d9-8ffe-0dfc63cee87f",
    "event": "Punch Out"
  },
  {
    "datetime": "2025-10-01T08:17:07",
    "name": "Manesh Chindarkar",
    "user_id": "ba1c916b-8e81-48d9-8ffe-0dfc63cee87f",
    "event": "Break Start"
  },
  {
    "datetime": "2025-10-01T09:08:56",
    "name": "Manesh Chindarkar",
    "user_id": "ba1c916b-8e81-48d9-8ffe-0dfc63cee87f",
    "event": "Break End"
  },
  {
    "datetime": "2025-10-01T05:23:40",
    "name": "Joshua Dsouza",
    "user_id": "7e559b4c-660d-4e63-a8b2-0c223c968ce3",
    "event": "Punch In"
  },
  {
    "datetime": "2025-10-01T14:34:53",
    "name": "Joshua Dsouza",
    "user_id": "7e559b4c-660d-4e63-a8b2-0c223c968ce3",
    "event": "Punch Out"
  },
  {
    "datetime": "2025-10-01T09:02:18",
    "name": "Joshua Dsouza",
    "user_id": "7e559b4c-660d-4e63-a8b2-0c223c968ce3",
    "event": "Break Start"
  },
  {
    "datetime": "2025-10-01T09:40:46",
    "name": "Joshua Dsouza",
    "user_id": "7e559b4c-660d-4e63-a8b2-0c223c968ce3",
    "event": "Break End"
  },
  {
    "datetime": "2025-10-01T12:26:01",
    "name": "Joshua Dsouza",
    "user_id": "7e559b4c-660d-4e63-a8b2-0c223c968ce3",
    "event": "Break Start"
  },
  {
    "datetime": "2025-10-01T12:38:52",
    "name": "Joshua Dsouza",
    "user_id": "7e559b4c-660d-4e63-a8b2-0c223c968ce3",
    "event": "Break End"
  },
  {
    "datetime": "2025-10-02T04:34:59",
    "name": "Akash Gitaye",
    "user_id": "a53a173f-9a7c-4c4b-875d-7c8edb5b6b7e",
    "event": "Punch In"
  },
  {
    "datetime": "2025-10-02T13:41:39",
    "name": "Akash Gitaye",
    "user_id": "a53a173f-9a7c-4c4b-875d-7c8edb5b6b7e",
    "event": "Punch Out"
  },
  {
    "datetime": "2025-10-02T10:18:10",
    "name": "Akash Gitaye",
    "user_id": "a53a173f-9a7c-4c4b-875d-7c8edb5b6b7e",
    "event": "Break Start"
  },
  {
    "datetime": "2025-10-02T11:15:06",
    "name": "Akash Gitaye",
    "user_id": "a53a173f-9a7c-4c4b-875d-7c8edb5b6b7e",
    "event": "Break End"
  },
  {
    "datetime": "2025-10-02T13:41:34",
    "name": "Akash Gitaye",
    "user_id": "a53a173f-9a7c-4c4b-875d-7c8edb5b6b7e",
    "event": "Break Start"
  },
  {
    "datetime": "2025-10-02T13:41:37",
    "name": "Akash Gitaye",
    "user_id": "a53a173f-9a7c-4c4b-875d-7c8edb5b6b7e",
    "event": "Break End"
  },
  {
    "datetime": "2025-10-03T04:33:03",
    "name": "Shubham Jadhav",
    "user_id": "27b0e2c7-9bdf-44a8-b930-8b3eba44d402",
    "event": "Punch In"
  },
  {
    "datetime": "2025-10-03T13:49:23",
    "name": "Shubham Jadhav",
    "user_id": "27b0e2c7-9bdf-44a8-b930-8b3eba44d402",
    "event": "Punch Out"
  },
  {
    "datetime": "2025-10-03T05:26:21",
    "name": "Shawn Nadar",
    "user_id": "e28c464b-50b3-41ad-8632-3322ce0f5eed",
    "event": "Punch In"
  },
  {
    "datetime": "2025-10-03T12:36:28",
    "name": "Shawn Nadar",
    "user_id": "e28c464b-50b3-41ad-8632-3322ce0f5eed",
    "event": "Punch Out"
  },
  {
    "datetime": "2025-10-03T08:57:43",
    "name": "Shawn Nadar",
    "user_id": "e28c464b-50b3-41ad-8632-3322ce0f5eed",
    "event": "Break Start"
  },
  {
    "datetime": "2025-10-03T09:56:21",
    "name": "Shawn Nadar",
    "user_id": "e28c464b-50b3-41ad-8632-3322ce0f5eed",
    "event": "Break End"
  },
  {
    "datetime": "2025-10-03T05:27:21",
    "name": "Manesh Chindarkar",
    "user_id": "ba1c916b-8e81-48d9-8ffe-0dfc63cee87f",
    "event": "Punch In"
  },
  {
    "datetime": "2025-10-03T14:39:32",
    "name": "Manesh Chindarkar",
    "user_id": "ba1c916b-8e81-48d9-8ffe-0dfc63cee87f",
    "event": "Punch Out"
  },
  {
    "datetime": "2025-10-03T04:30:00",
    "name": "Akash Gitaye",
    "user_id": "a53a173f-9a7c-4c4b-875d-7c8edb5b6b7e",
    "event": "Punch In"
  },
  {
    "datetime": "2025-10-03T14:33:34",
    "name": "Akash Gitaye",
    "user_id": "a53a173f-9a7c-4c4b-875d-7c8edb5b6b7e",
    "event": "Punch Out"
  },
  {
    "datetime": "2025-10-03T10:32:38",
    "name": "Akash Gitaye",
    "user_id": "a53a173f-9a7c-4c4b-875d-7c8edb5b6b7e",
    "event": "Break Start"
  },
  {
    "datetime": "2025-10-03T11:02:32",
    "name": "Akash Gitaye",
    "user_id": "a53a173f-9a7c-4c4b-875d-7c8edb5b6b7e",
    "event": "Break End"
  },
  {
    "datetime": "2025-10-03T05:32:14",
    "name": "Joshua Dsouza",
    "user_id": "7e559b4c-660d-4e63-a8b2-0c223c968ce3",
    "event": "Punch In"
  },
  {
    "datetime": "2025-10-03T14:37:53",
    "name": "Joshua Dsouza",
    "user_id": "7e559b4c-660d-4e63-a8b2-0c223c968ce3",
    "event": "Punch Out"
  },
  {
    "datetime": "2025-10-03T09:37:11",
    "name": "Joshua Dsouza",
    "user_id": "7e559b4c-660d-4e63-a8b2-0c223c968ce3",
    "event": "Break Start"
  },
  {
    "datetime": "2025-10-03T10:18:41",
    "name": "Joshua Dsouza",
    "user_id": "7e559b4c-660d-4e63-a8b2-0c223c968ce3",
    "event": "Break End"
  },
  {
    "datetime": "2025-10-03T07:16:07",
    "name": "Gaurav Ghadi",
    "user_id": "5d2d7843-9744-4fb5-948b-73cc554a92dc",
    "event": "Punch In"
  },
  {
    "datetime": "2025-10-10T05:23:05",
    "name": "Gaurav Ghadi",
    "user_id": "5d2d7843-9744-4fb5-948b-73cc554a92dc",
    "event": "Punch Out"
  },
  {
    "datetime": "2025-10-03T08:01:24",
    "name": "Gaurav Ghadi",
    "user_id": "5d2d7843-9744-4fb5-948b-73cc554a92dc",
    "event": "Break Start"
  },
  {
    "datetime": "2025-10-03T08:09:39",
    "name": "Gaurav Ghadi",
    "user_id": "5d2d7843-9744-4fb5-948b-73cc554a92dc",
    "event": "Break End"
  },
  {
    "datetime": "2025-10-04T05:02:16",
    "name": "Manesh Chindarkar",
    "user_id": "ba1c916b-8e81-48d9-8ffe-0dfc63cee87f",
    "event": "Punch In"
  },
  {
    "datetime": "2025-10-04T11:41:17",
    "name": "Manesh Chindarkar",
    "user_id": "ba1c916b-8e81-48d9-8ffe-0dfc63cee87f",
    "event": "Punch Out"
  },
  {
    "datetime": "2025-10-06T04:26:12",
    "name": "Akash Gitaye",
    "user_id": "a53a173f-9a7c-4c4b-875d-7c8edb5b6b7e",
    "event": "Punch In"
  },
  {
    "datetime": "2025-10-06T14:23:51",
    "name": "Akash Gitaye",
    "user_id": "a53a173f-9a7c-4c4b-875d-7c8edb5b6b7e",
    "event": "Punch Out"
  },
  {
    "datetime": "2025-10-06T08:58:39",
    "name": "Akash Gitaye",
    "user_id": "a53a173f-9a7c-4c4b-875d-7c8edb5b6b7e",
    "event": "Break Start"
  },
  {
    "datetime": "2025-10-06T09:58:59",
    "name": "Akash Gitaye",
    "user_id": "a53a173f-9a7c-4c4b-875d-7c8edb5b6b7e",
    "event": "Break End"
  },
  {
    "datetime": "2025-10-06T04:26:25",
    "name": "Shubham Jadhav",
    "user_id": "27b0e2c7-9bdf-44a8-b930-8b3eba44d402",
    "event": "Punch In"
  },
  {
    "datetime": "2025-10-06T13:41:06",
    "name": "Shubham Jadhav",
    "user_id": "27b0e2c7-9bdf-44a8-b930-8b3eba44d402",
    "event": "Punch Out"
  },
  {
    "datetime": "2025-10-06T08:57:21",
    "name": "Shubham Jadhav",
    "user_id": "27b0e2c7-9bdf-44a8-b930-8b3eba44d402",
    "event": "Break Start"
  },
  {
    "datetime": "2025-10-06T10:03:52",
    "name": "Shubham Jadhav",
    "user_id": "27b0e2c7-9bdf-44a8-b930-8b3eba44d402",
    "event": "Break End"
  },
  {
    "datetime": "2025-10-06T05:15:31",
    "name": "Manesh Chindarkar",
    "user_id": "ba1c916b-8e81-48d9-8ffe-0dfc63cee87f",
    "event": "Punch In"
  },
  {
    "datetime": "2025-10-06T14:31:56",
    "name": "Manesh Chindarkar",
    "user_id": "ba1c916b-8e81-48d9-8ffe-0dfc63cee87f",
    "event": "Punch Out"
  },
  {
    "datetime": "2025-10-06T08:56:57",
    "name": "Manesh Chindarkar",
    "user_id": "ba1c916b-8e81-48d9-8ffe-0dfc63cee87f",
    "event": "Break Start"
  },
  {
    "datetime": "2025-10-06T10:09:17",
    "name": "Manesh Chindarkar",
    "user_id": "ba1c916b-8e81-48d9-8ffe-0dfc63cee87f",
    "event": "Break End"
  },
  {
    "datetime": "2025-10-06T06:00:15",
    "name": "Shawn Nadar",
    "user_id": "e28c464b-50b3-41ad-8632-3322ce0f5eed",
    "event": "Punch In"
  },
  {
    "datetime": "2025-10-06T15:00:07",
    "name": "Shawn Nadar",
    "user_id": "e28c464b-50b3-41ad-8632-3322ce0f5eed",
    "event": "Punch Out"
  },
  {
    "datetime": "2025-10-06T08:50:03",
    "name": "Shawn Nadar",
    "user_id": "e28c464b-50b3-41ad-8632-3322ce0f5eed",
    "event": "Break Start"
  },
  {
    "datetime": "2025-10-06T09:10:06",
    "name": "Shawn Nadar",
    "user_id": "e28c464b-50b3-41ad-8632-3322ce0f5eed",
    "event": "Break End"
  },
  {
    "datetime": "2025-10-06T14:00:35",
    "name": "Shawn Nadar",
    "user_id": "e28c464b-50b3-41ad-8632-3322ce0f5eed",
    "event": "Break Start"
  },
  {
    "datetime": "2025-10-06T14:35:49",
    "name": "Shawn Nadar",
    "user_id": "e28c464b-50b3-41ad-8632-3322ce0f5eed",
    "event": "Break End"
  },
  {
    "datetime": "2025-10-06T06:04:02",
    "name": "Joshua Dsouza",
    "user_id": "7e559b4c-660d-4e63-a8b2-0c223c968ce3",
    "event": "Punch In"
  },
  {
    "datetime": "2025-10-06T14:38:15",
    "name": "Joshua Dsouza",
    "user_id": "7e559b4c-660d-4e63-a8b2-0c223c968ce3",
    "event": "Punch Out"
  },
  {
    "datetime": "2025-10-06T10:16:59",
    "name": "Joshua Dsouza",
    "user_id": "7e559b4c-660d-4e63-a8b2-0c223c968ce3",
    "event": "Break Start"
  },
  {
    "datetime": "2025-10-06T10:52:57",
    "name": "Joshua Dsouza",
    "user_id": "7e559b4c-660d-4e63-a8b2-0c223c968ce3",
    "event": "Break End"
  },
  {
    "datetime": "2025-10-06T06:31:29",
    "name": "Suhas Kesari",
    "user_id": "53234bff-130a-44e9-b9a0-b1cfdb963c6f",
    "event": "Punch In"
  },
  {
    "datetime": "2025-10-08T14:31:28",
    "name": "Suhas Kesari",
    "user_id": "53234bff-130a-44e9-b9a0-b1cfdb963c6f",
    "event": "Punch Out"
  },
  {
    "datetime": "2025-10-06T09:08:28",
    "name": "Alizain Patel",
    "user_id": "e634f02e-1486-4ec5-9530-a92c2dc93ef8",
    "event": "Punch In"
  },
  {
    "datetime": "2025-10-07T10:03:43",
    "name": "Alizain Patel",
    "user_id": "e634f02e-1486-4ec5-9530-a92c2dc93ef8",
    "event": "Punch Out"
  },
  {
    "datetime": "2025-10-07T04:31:34",
    "name": "Akash Gitaye",
    "user_id": "a53a173f-9a7c-4c4b-875d-7c8edb5b6b7e",
    "event": "Punch In"
  },
  {
    "datetime": "2025-10-07T13:49:55",
    "name": "Akash Gitaye",
    "user_id": "a53a173f-9a7c-4c4b-875d-7c8edb5b6b7e",
    "event": "Punch Out"
  },
  {
    "datetime": "2025-10-07T08:30:46",
    "name": "Akash Gitaye",
    "user_id": "a53a173f-9a7c-4c4b-875d-7c8edb5b6b7e",
    "event": "Break Start"
  },
  {
    "datetime": "2025-10-07T09:16:38",
    "name": "Akash Gitaye",
    "user_id": "a53a173f-9a7c-4c4b-875d-7c8edb5b6b7e",
    "event": "Break End"
  },
  {
    "datetime": "2025-10-07T04:38:30",
    "name": "Shubham Jadhav",
    "user_id": "27b0e2c7-9bdf-44a8-b930-8b3eba44d402",
    "event": "Punch In"
  },
  {
    "datetime": "2025-10-07T13:50:14",
    "name": "Shubham Jadhav",
    "user_id": "27b0e2c7-9bdf-44a8-b930-8b3eba44d402",
    "event": "Punch Out"
  },
  {
    "datetime": "2025-10-07T08:41:39",
    "name": "Shubham Jadhav",
    "user_id": "27b0e2c7-9bdf-44a8-b930-8b3eba44d402",
    "event": "Break Start"
  },
  {
    "datetime": "2025-10-07T09:37:29",
    "name": "Shubham Jadhav",
    "user_id": "27b0e2c7-9bdf-44a8-b930-8b3eba44d402",
    "event": "Break End"
  },
  {
    "datetime": "2025-10-07T05:26:05",
    "name": "Joshua Dsouza",
    "user_id": "7e559b4c-660d-4e63-a8b2-0c223c968ce3",
    "event": "Punch In"
  },
  {
    "datetime": "2025-10-07T14:56:14",
    "name": "Joshua Dsouza",
    "user_id": "7e559b4c-660d-4e63-a8b2-0c223c968ce3",
    "event": "Punch Out"
  },
  {
    "datetime": "2025-10-07T09:40:03",
    "name": "Joshua Dsouza",
    "user_id": "7e559b4c-660d-4e63-a8b2-0c223c968ce3",
    "event": "Break Start"
  },
  {
    "datetime": "2025-10-07T10:13:14",
    "name": "Joshua Dsouza",
    "user_id": "7e559b4c-660d-4e63-a8b2-0c223c968ce3",
    "event": "Break End"
  },
  {
    "datetime": "2025-10-07T05:47:21",
    "name": "Manesh Chindarkar",
    "user_id": "ba1c916b-8e81-48d9-8ffe-0dfc63cee87f",
    "event": "Punch In"
  },
  {
    "datetime": "2025-10-07T14:58:42",
    "name": "Manesh Chindarkar",
    "user_id": "ba1c916b-8e81-48d9-8ffe-0dfc63cee87f",
    "event": "Punch Out"
  },
  {
    "datetime": "2025-10-07T08:29:41",
    "name": "Manesh Chindarkar",
    "user_id": "ba1c916b-8e81-48d9-8ffe-0dfc63cee87f",
    "event": "Break Start"
  },
  {
    "datetime": "2025-10-07T09:31:57",
    "name": "Manesh Chindarkar",
    "user_id": "ba1c916b-8e81-48d9-8ffe-0dfc63cee87f",
    "event": "Break End"
  },
  {
    "datetime": "2025-10-07T06:00:04",
    "name": "Shawn Nadar",
    "user_id": "e28c464b-50b3-41ad-8632-3322ce0f5eed",
    "event": "Punch In"
  },
  {
    "datetime": "2025-10-07T15:02:26",
    "name": "Shawn Nadar",
    "user_id": "e28c464b-50b3-41ad-8632-3322ce0f5eed",
    "event": "Punch Out"
  },
  {
    "datetime": "2025-10-07T09:10:26",
    "name": "Shawn Nadar",
    "user_id": "e28c464b-50b3-41ad-8632-3322ce0f5eed",
    "event": "Break Start"
  },
  {
    "datetime": "2025-10-07T09:30:30",
    "name": "Shawn Nadar",
    "user_id": "e28c464b-50b3-41ad-8632-3322ce0f5eed",
    "event": "Break End"
  },
  {
    "datetime": "2025-10-07T14:00:06",
    "name": "Shawn Nadar",
    "user_id": "e28c464b-50b3-41ad-8632-3322ce0f5eed",
    "event": "Break Start"
  },
  {
    "datetime": "2025-10-07T14:35:38",
    "name": "Shawn Nadar",
    "user_id": "e28c464b-50b3-41ad-8632-3322ce0f5eed",
    "event": "Break End"
  },
  {
    "datetime": "2025-10-08T04:32:43",
    "name": "Akash Gitaye",
    "user_id": "a53a173f-9a7c-4c4b-875d-7c8edb5b6b7e",
    "event": "Punch In"
  },
  {
    "datetime": "2025-10-08T14:24:37",
    "name": "Akash Gitaye",
    "user_id": "a53a173f-9a7c-4c4b-875d-7c8edb5b6b7e",
    "event": "Punch Out"
  },
  {
    "datetime": "2025-10-08T07:51:07",
    "name": "Akash Gitaye",
    "user_id": "a53a173f-9a7c-4c4b-875d-7c8edb5b6b7e",
    "event": "Break Start"
  },
  {
    "datetime": "2025-10-08T14:24:07",
    "name": "Akash Gitaye",
    "user_id": "a53a173f-9a7c-4c4b-875d-7c8edb5b6b7e",
    "event": "Break End"
  },
  {
    "datetime": "2025-10-08T04:42:16",
    "name": "Shubham Jadhav",
    "user_id": "27b0e2c7-9bdf-44a8-b930-8b3eba44d402",
    "event": "Punch In"
  },
  {
    "datetime": "2025-10-08T13:47:45",
    "name": "Shubham Jadhav",
    "user_id": "27b0e2c7-9bdf-44a8-b930-8b3eba44d402",
    "event": "Punch Out"
  },
  {
    "datetime": "2025-10-08T07:50:52",
    "name": "Shubham Jadhav",
    "user_id": "27b0e2c7-9bdf-44a8-b930-8b3eba44d402",
    "event": "Break Start"
  },
  {
    "datetime": "2025-10-08T08:47:34",
    "name": "Shubham Jadhav",
    "user_id": "27b0e2c7-9bdf-44a8-b930-8b3eba44d402",
    "event": "Break End"
  },
  {
    "datetime": "2025-10-08T05:33:29",
    "name": "Manesh Chindarkar",
    "user_id": "ba1c916b-8e81-48d9-8ffe-0dfc63cee87f",
    "event": "Punch In"
  },
  {
    "datetime": "2025-10-08T15:00:17",
    "name": "Manesh Chindarkar",
    "user_id": "ba1c916b-8e81-48d9-8ffe-0dfc63cee87f",
    "event": "Punch Out"
  },
  {
    "datetime": "2025-10-08T07:47:51",
    "name": "Manesh Chindarkar",
    "user_id": "ba1c916b-8e81-48d9-8ffe-0dfc63cee87f",
    "event": "Break Start"
  },
  {
    "datetime": "2025-10-08T08:42:44",
    "name": "Manesh Chindarkar",
    "user_id": "ba1c916b-8e81-48d9-8ffe-0dfc63cee87f",
    "event": "Break End"
  },
  {
    "datetime": "2025-10-08T05:48:32",
    "name": "Joshua Dsouza",
    "user_id": "7e559b4c-660d-4e63-a8b2-0c223c968ce3",
    "event": "Punch In"
  },
  {
    "datetime": "2025-10-08T15:27:14",
    "name": "Joshua Dsouza",
    "user_id": "7e559b4c-660d-4e63-a8b2-0c223c968ce3",
    "event": "Punch Out"
  },
  {
    "datetime": "2025-10-08T08:49:43",
    "name": "Joshua Dsouza",
    "user_id": "7e559b4c-660d-4e63-a8b2-0c223c968ce3",
    "event": "Break Start"
  },
  {
    "datetime": "2025-10-08T09:23:24",
    "name": "Joshua Dsouza",
    "user_id": "7e559b4c-660d-4e63-a8b2-0c223c968ce3",
    "event": "Break End"
  },
  {
    "datetime": "2025-10-08T12:32:57",
    "name": "Joshua Dsouza",
    "user_id": "7e559b4c-660d-4e63-a8b2-0c223c968ce3",
    "event": "Break Start"
  },
  {
    "datetime": "2025-10-08T12:53:28",
    "name": "Joshua Dsouza",
    "user_id": "7e559b4c-660d-4e63-a8b2-0c223c968ce3",
    "event": "Break End"
  },
  {
    "datetime": "2025-10-08T06:00:03",
    "name": "Shawn Nadar",
    "user_id": "e28c464b-50b3-41ad-8632-3322ce0f5eed",
    "event": "Punch In"
  },
  {
    "datetime": "2025-10-08T15:01:17",
    "name": "Shawn Nadar",
    "user_id": "e28c464b-50b3-41ad-8632-3322ce0f5eed",
    "event": "Punch Out"
  },
  {
    "datetime": "2025-10-08T09:10:07",
    "name": "Shawn Nadar",
    "user_id": "e28c464b-50b3-41ad-8632-3322ce0f5eed",
    "event": "Break Start"
  },
  {
    "datetime": "2025-10-08T09:30:04",
    "name": "Shawn Nadar",
    "user_id": "e28c464b-50b3-41ad-8632-3322ce0f5eed",
    "event": "Break End"
  },
  {
    "datetime": "2025-10-08T10:48:38",
    "name": "priti surve",
    "user_id": "f42e59a6-745d-4efd-acc7-95946783d281",
    "event": "Punch In"
  },
  {
    "datetime": "2025-10-15T05:40:04",
    "name": "priti surve",
    "user_id": "f42e59a6-745d-4efd-acc7-95946783d281",
    "event": "Punch Out"
  },
  {
    "datetime": "2025-10-09T04:33:55",
    "name": "Akash Gitaye",
    "user_id": "a53a173f-9a7c-4c4b-875d-7c8edb5b6b7e",
    "event": "Punch In"
  },
  {
    "datetime": "2025-10-09T13:52:43",
    "name": "Akash Gitaye",
    "user_id": "a53a173f-9a7c-4c4b-875d-7c8edb5b6b7e",
    "event": "Punch Out"
  },
  {
    "datetime": "2025-10-09T09:02:18",
    "name": "Akash Gitaye",
    "user_id": "a53a173f-9a7c-4c4b-875d-7c8edb5b6b7e",
    "event": "Break Start"
  },
  {
    "datetime": "2025-10-09T09:52:41",
    "name": "Akash Gitaye",
    "user_id": "a53a173f-9a7c-4c4b-875d-7c8edb5b6b7e",
    "event": "Break End"
  },
  {
    "datetime": "2025-10-09T04:36:12",
    "name": "Shubham Jadhav",
    "user_id": "27b0e2c7-9bdf-44a8-b930-8b3eba44d402",
    "event": "Punch In"
  },
  {
    "datetime": "2025-10-09T13:35:58",
    "name": "Shubham Jadhav",
    "user_id": "27b0e2c7-9bdf-44a8-b930-8b3eba44d402",
    "event": "Punch Out"
  },
  {
    "datetime": "2025-10-09T09:02:10",
    "name": "Shubham Jadhav",
    "user_id": "27b0e2c7-9bdf-44a8-b930-8b3eba44d402",
    "event": "Break Start"
  },
  {
    "datetime": "2025-10-09T10:00:03",
    "name": "Shubham Jadhav",
    "user_id": "27b0e2c7-9bdf-44a8-b930-8b3eba44d402",
    "event": "Break End"
  },
  {
    "datetime": "2025-10-09T05:36:34",
    "name": "Joshua Dsouza",
    "user_id": "7e559b4c-660d-4e63-a8b2-0c223c968ce3",
    "event": "Punch In"
  },
  {
    "datetime": "2025-10-09T14:33:25",
    "name": "Joshua Dsouza",
    "user_id": "7e559b4c-660d-4e63-a8b2-0c223c968ce3",
    "event": "Punch Out"
  },
  {
    "datetime": "2025-10-09T10:18:06",
    "name": "Joshua Dsouza",
    "user_id": "7e559b4c-660d-4e63-a8b2-0c223c968ce3",
    "event": "Break Start"
  },
  {
    "datetime": "2025-10-09T10:55:25",
    "name": "Joshua Dsouza",
    "user_id": "7e559b4c-660d-4e63-a8b2-0c223c968ce3",
    "event": "Break End"
  },
  {
    "datetime": "2025-10-09T05:40:54",
    "name": "Suhas Kesari",
    "user_id": "53234bff-130a-44e9-b9a0-b1cfdb963c6f",
    "event": "Punch In"
  },
  {
    "datetime": "2025-10-09T14:30:31",
    "name": "Suhas Kesari",
    "user_id": "53234bff-130a-44e9-b9a0-b1cfdb963c6f",
    "event": "Punch Out"
  },
  {
    "datetime": "2025-10-09T05:47:56",
    "name": "Manesh Chindarkar",
    "user_id": "ba1c916b-8e81-48d9-8ffe-0dfc63cee87f",
    "event": "Punch In"
  },
  {
    "datetime": "2025-10-09T14:33:23",
    "name": "Manesh Chindarkar",
    "user_id": "ba1c916b-8e81-48d9-8ffe-0dfc63cee87f",
    "event": "Punch Out"
  },
  {
    "datetime": "2025-10-09T09:01:29",
    "name": "Manesh Chindarkar",
    "user_id": "ba1c916b-8e81-48d9-8ffe-0dfc63cee87f",
    "event": "Break Start"
  },
  {
    "datetime": "2025-10-09T10:00:11",
    "name": "Manesh Chindarkar",
    "user_id": "ba1c916b-8e81-48d9-8ffe-0dfc63cee87f",
    "event": "Break End"
  },
  {
    "datetime": "2025-10-09T06:00:04",
    "name": "Shawn Nadar",
    "user_id": "e28c464b-50b3-41ad-8632-3322ce0f5eed",
    "event": "Punch In"
  },
  {
    "datetime": "2025-10-09T15:00:35",
    "name": "Shawn Nadar",
    "user_id": "e28c464b-50b3-41ad-8632-3322ce0f5eed",
    "event": "Punch Out"
  },
  {
    "datetime": "2025-10-09T09:00:12",
    "name": "Shawn Nadar",
    "user_id": "e28c464b-50b3-41ad-8632-3322ce0f5eed",
    "event": "Break Start"
  },
  {
    "datetime": "2025-10-09T09:28:55",
    "name": "Shawn Nadar",
    "user_id": "e28c464b-50b3-41ad-8632-3322ce0f5eed",
    "event": "Break End"
  },
  {
    "datetime": "2025-10-09T14:00:07",
    "name": "Shawn Nadar",
    "user_id": "e28c464b-50b3-41ad-8632-3322ce0f5eed",
    "event": "Break Start"
  },
  {
    "datetime": "2025-10-09T14:29:29",
    "name": "Shawn Nadar",
    "user_id": "e28c464b-50b3-41ad-8632-3322ce0f5eed",
    "event": "Break End"
  },
  {
    "datetime": "2025-10-09T09:21:21",
    "name": "Alizain Patel",
    "user_id": "e634f02e-1486-4ec5-9530-a92c2dc93ef8",
    "event": "Punch In"
  },
  {
    "datetime": "2025-10-09T14:30:42",
    "name": "Alizain Patel",
    "user_id": "e634f02e-1486-4ec5-9530-a92c2dc93ef8",
    "event": "Punch Out"
  },
  {
    "datetime": "2025-10-09T09:25:08",
    "name": "Alizain Patel",
    "user_id": "e634f02e-1486-4ec5-9530-a92c2dc93ef8",
    "event": "Break Start"
  },
  {
    "datetime": "2025-10-09T09:25:14",
    "name": "Alizain Patel",
    "user_id": "e634f02e-1486-4ec5-9530-a92c2dc93ef8",
    "event": "Break End"
  },
  {
    "datetime": "2025-10-09T13:20:09",
    "name": "Alizain Patel",
    "user_id": "e634f02e-1486-4ec5-9530-a92c2dc93ef8",
    "event": "Break Start"
  },
  {
    "datetime": "2025-10-09T13:21:24",
    "name": "Alizain Patel",
    "user_id": "e634f02e-1486-4ec5-9530-a92c2dc93ef8",
    "event": "Break End"
  },
  {
    "datetime": "2025-10-10T04:32:26",
    "name": "Shubham Jadhav",
    "user_id": "27b0e2c7-9bdf-44a8-b930-8b3eba44d402",
    "event": "Punch In"
  },
  {
    "datetime": "2025-10-10T15:01:41",
    "name": "Shubham Jadhav",
    "user_id": "27b0e2c7-9bdf-44a8-b930-8b3eba44d402",
    "event": "Punch Out"
  },
  {
    "datetime": "2025-10-10T09:07:53",
    "name": "Shubham Jadhav",
    "user_id": "27b0e2c7-9bdf-44a8-b930-8b3eba44d402",
    "event": "Break Start"
  },
  {
    "datetime": "2025-10-10T10:13:45",
    "name": "Shubham Jadhav",
    "user_id": "27b0e2c7-9bdf-44a8-b930-8b3eba44d402",
    "event": "Break End"
  },
  {
    "datetime": "2025-10-10T04:32:56",
    "name": "Akash Gitaye",
    "user_id": "a53a173f-9a7c-4c4b-875d-7c8edb5b6b7e",
    "event": "Punch In"
  },
  {
    "datetime": "2025-10-10T14:54:40",
    "name": "Akash Gitaye",
    "user_id": "a53a173f-9a7c-4c4b-875d-7c8edb5b6b7e",
    "event": "Punch Out"
  },
  {
    "datetime": "2025-10-10T09:08:53",
    "name": "Akash Gitaye",
    "user_id": "a53a173f-9a7c-4c4b-875d-7c8edb5b6b7e",
    "event": "Break Start"
  },
  {
    "datetime": "2025-10-10T09:55:11",
    "name": "Akash Gitaye",
    "user_id": "a53a173f-9a7c-4c4b-875d-7c8edb5b6b7e",
    "event": "Break End"
  },
  {
    "datetime": "2025-10-10T05:17:48",
    "name": "Manesh Chindarkar",
    "user_id": "ba1c916b-8e81-48d9-8ffe-0dfc63cee87f",
    "event": "Punch In"
  },
  {
    "datetime": "2025-10-10T14:51:50",
    "name": "Manesh Chindarkar",
    "user_id": "ba1c916b-8e81-48d9-8ffe-0dfc63cee87f",
    "event": "Punch Out"
  },
  {
    "datetime": "2025-10-10T09:08:31",
    "name": "Manesh Chindarkar",
    "user_id": "ba1c916b-8e81-48d9-8ffe-0dfc63cee87f",
    "event": "Break Start"
  },
  {
    "datetime": "2025-10-10T10:16:51",
    "name": "Manesh Chindarkar",
    "user_id": "ba1c916b-8e81-48d9-8ffe-0dfc63cee87f",
    "event": "Break End"
  },
  {
    "datetime": "2025-10-10T05:23:12",
    "name": "Gaurav Ghadi",
    "user_id": "5d2d7843-9744-4fb5-948b-73cc554a92dc",
    "event": "Punch In"
  },
  {
    "datetime": "2025-10-14T05:01:26",
    "name": "Gaurav Ghadi",
    "user_id": "5d2d7843-9744-4fb5-948b-73cc554a92dc",
    "event": "Punch Out"
  },
  {
    "datetime": "2025-10-10T05:28:26",
    "name": "Alizain Patel",
    "user_id": "e634f02e-1486-4ec5-9530-a92c2dc93ef8",
    "event": "Punch In"
  },
  {
    "datetime": "2025-10-10T14:34:54",
    "name": "Alizain Patel",
    "user_id": "e634f02e-1486-4ec5-9530-a92c2dc93ef8",
    "event": "Punch Out"
  },
  {
    "datetime": "2025-10-10T06:43:37",
    "name": "Alizain Patel",
    "user_id": "e634f02e-1486-4ec5-9530-a92c2dc93ef8",
    "event": "Break Start"
  },
  {
    "datetime": "2025-10-10T09:01:08",
    "name": "Alizain Patel",
    "user_id": "e634f02e-1486-4ec5-9530-a92c2dc93ef8",
    "event": "Break End"
  },
  {
    "datetime": "2025-10-10T05:35:35",
    "name": "Suhas Kesari",
    "user_id": "53234bff-130a-44e9-b9a0-b1cfdb963c6f",
    "event": "Punch In"
  },
  {
    "datetime": "2025-10-12T07:50:12",
    "name": "Suhas Kesari",
    "user_id": "53234bff-130a-44e9-b9a0-b1cfdb963c6f",
    "event": "Punch Out"
  },
  {
    "datetime": "2025-10-10T05:46:59",
    "name": "Joshua Dsouza",
    "user_id": "7e559b4c-660d-4e63-a8b2-0c223c968ce3",
    "event": "Punch In"
  },
  {
    "datetime": "2025-10-10T08:49:16",
    "name": "Joshua Dsouza",
    "user_id": "7e559b4c-660d-4e63-a8b2-0c223c968ce3",
    "event": "Punch Out"
  },
  {
    "datetime": "2025-10-10T07:50:05",
    "name": "Joshua Dsouza",
    "user_id": "7e559b4c-660d-4e63-a8b2-0c223c968ce3",
    "event": "Break Start"
  },
  {
    "datetime": "2025-10-10T08:38:40",
    "name": "Joshua Dsouza",
    "user_id": "7e559b4c-660d-4e63-a8b2-0c223c968ce3",
    "event": "Break End"
  },
  {
    "datetime": "2025-10-10T05:59:59",
    "name": "Shawn Nadar",
    "user_id": "e28c464b-50b3-41ad-8632-3322ce0f5eed",
    "event": "Punch In"
  },
  {
    "datetime": "2025-10-10T15:01:59",
    "name": "Shawn Nadar",
    "user_id": "e28c464b-50b3-41ad-8632-3322ce0f5eed",
    "event": "Punch Out"
  },
  {
    "datetime": "2025-10-10T10:50:49",
    "name": "Shawn Nadar",
    "user_id": "e28c464b-50b3-41ad-8632-3322ce0f5eed",
    "event": "Break Start"
  },
  {
    "datetime": "2025-10-10T11:04:09",
    "name": "Shawn Nadar",
    "user_id": "e28c464b-50b3-41ad-8632-3322ce0f5eed",
    "event": "Break End"
  },
  {
    "datetime": "2025-10-10T12:05:28",
    "name": "Shawn Nadar",
    "user_id": "e28c464b-50b3-41ad-8632-3322ce0f5eed",
    "event": "Break Start"
  },
  {
    "datetime": "2025-10-10T12:33:27",
    "name": "Shawn Nadar",
    "user_id": "e28c464b-50b3-41ad-8632-3322ce0f5eed",
    "event": "Break End"
  },
  {
    "datetime": "2025-10-10T06:08:00",
    "name": "Mayur Divekar",
    "user_id": "8b67200f-f49b-47e3-ba26-5f38e2c99501",
    "event": "Punch In"
  },
  {
    "datetime": "2025-10-10T14:36:34",
    "name": "Mayur Divekar",
    "user_id": "8b67200f-f49b-47e3-ba26-5f38e2c99501",
    "event": "Punch Out"
  },
  {
    "datetime": "2025-10-13T04:36:03",
    "name": "Akash Gitaye",
    "user_id": "a53a173f-9a7c-4c4b-875d-7c8edb5b6b7e",
    "event": "Punch In"
  },
  {
    "datetime": "2025-10-13T13:56:29",
    "name": "Akash Gitaye",
    "user_id": "a53a173f-9a7c-4c4b-875d-7c8edb5b6b7e",
    "event": "Punch Out"
  },
  {
    "datetime": "2025-10-13T08:08:39",
    "name": "Akash Gitaye",
    "user_id": "a53a173f-9a7c-4c4b-875d-7c8edb5b6b7e",
    "event": "Break Start"
  },
  {
    "datetime": "2025-10-13T09:02:29",
    "name": "Akash Gitaye",
    "user_id": "a53a173f-9a7c-4c4b-875d-7c8edb5b6b7e",
    "event": "Break End"
  },
  {
    "datetime": "2025-10-13T04:55:12",
    "name": "Shubham Jadhav",
    "user_id": "27b0e2c7-9bdf-44a8-b930-8b3eba44d402",
    "event": "Punch In"
  },
  {
    "datetime": "2025-10-13T14:30:00",
    "name": "Shubham Jadhav",
    "user_id": "27b0e2c7-9bdf-44a8-b930-8b3eba44d402",
    "event": "Punch Out"
  },
  {
    "datetime": "2025-10-13T08:08:31",
    "name": "Shubham Jadhav",
    "user_id": "27b0e2c7-9bdf-44a8-b930-8b3eba44d402",
    "event": "Break Start"
  },
  {
    "datetime": "2025-10-13T09:13:12",
    "name": "Shubham Jadhav",
    "user_id": "27b0e2c7-9bdf-44a8-b930-8b3eba44d402",
    "event": "Break End"
  },
  {
    "datetime": "2025-10-13T05:12:44",
    "name": "Shawn Nadar",
    "user_id": "e28c464b-50b3-41ad-8632-3322ce0f5eed",
    "event": "Punch In"
  },
  {
    "datetime": "2025-10-13T14:48:55",
    "name": "Shawn Nadar",
    "user_id": "e28c464b-50b3-41ad-8632-3322ce0f5eed",
    "event": "Punch Out"
  },
  {
    "datetime": "2025-10-13T09:13:32",
    "name": "Shawn Nadar",
    "user_id": "e28c464b-50b3-41ad-8632-3322ce0f5eed",
    "event": "Break Start"
  },
  {
    "datetime": "2025-10-13T09:48:59",
    "name": "Shawn Nadar",
    "user_id": "e28c464b-50b3-41ad-8632-3322ce0f5eed",
    "event": "Break End"
  },
  {
    "datetime": "2025-10-13T13:34:37",
    "name": "Shawn Nadar",
    "user_id": "e28c464b-50b3-41ad-8632-3322ce0f5eed",
    "event": "Break Start"
  },
  {
    "datetime": "2025-10-13T13:49:50",
    "name": "Shawn Nadar",
    "user_id": "e28c464b-50b3-41ad-8632-3322ce0f5eed",
    "event": "Break End"
  },
  {
    "datetime": "2025-10-13T05:21:03",
    "name": "Alizain Patel",
    "user_id": "e634f02e-1486-4ec5-9530-a92c2dc93ef8",
    "event": "Punch In"
  },
  {
    "datetime": "2025-10-13T14:36:35",
    "name": "Alizain Patel",
    "user_id": "e634f02e-1486-4ec5-9530-a92c2dc93ef8",
    "event": "Punch Out"
  },
  {
    "datetime": "2025-10-13T05:30:17",
    "name": "Manesh Chindarkar",
    "user_id": "ba1c916b-8e81-48d9-8ffe-0dfc63cee87f",
    "event": "Punch In"
  },
  {
    "datetime": "2025-10-13T14:32:09",
    "name": "Manesh Chindarkar",
    "user_id": "ba1c916b-8e81-48d9-8ffe-0dfc63cee87f",
    "event": "Punch Out"
  },
  {
    "datetime": "2025-10-13T08:07:20",
    "name": "Manesh Chindarkar",
    "user_id": "ba1c916b-8e81-48d9-8ffe-0dfc63cee87f",
    "event": "Break Start"
  },
  {
    "datetime": "2025-10-13T09:06:47",
    "name": "Manesh Chindarkar",
    "user_id": "ba1c916b-8e81-48d9-8ffe-0dfc63cee87f",
    "event": "Break End"
  },
  {
    "datetime": "2025-10-13T05:57:58",
    "name": "Mayur Divekar",
    "user_id": "8b67200f-f49b-47e3-ba26-5f38e2c99501",
    "event": "Punch In"
  },
  {
    "datetime": "2025-10-13T14:44:05",
    "name": "Mayur Divekar",
    "user_id": "8b67200f-f49b-47e3-ba26-5f38e2c99501",
    "event": "Punch Out"
  },
  {
    "datetime": "2025-10-13T06:01:39",
    "name": "Suhas Kesari",
    "user_id": "53234bff-130a-44e9-b9a0-b1cfdb963c6f",
    "event": "Punch In"
  },
  {
    "datetime": "2025-10-13T15:33:37",
    "name": "Suhas Kesari",
    "user_id": "53234bff-130a-44e9-b9a0-b1cfdb963c6f",
    "event": "Punch Out"
  },
  {
    "datetime": "2025-10-14T04:32:13",
    "name": "Akash Gitaye",
    "user_id": "a53a173f-9a7c-4c4b-875d-7c8edb5b6b7e",
    "event": "Punch In"
  },
  {
    "datetime": "2025-10-14T14:15:17",
    "name": "Akash Gitaye",
    "user_id": "a53a173f-9a7c-4c4b-875d-7c8edb5b6b7e",
    "event": "Punch Out"
  },
  {
    "datetime": "2025-10-14T08:30:14",
    "name": "Akash Gitaye",
    "user_id": "a53a173f-9a7c-4c4b-875d-7c8edb5b6b7e",
    "event": "Break Start"
  },
  {
    "datetime": "2025-10-14T09:29:54",
    "name": "Akash Gitaye",
    "user_id": "a53a173f-9a7c-4c4b-875d-7c8edb5b6b7e",
    "event": "Break End"
  },
  {
    "datetime": "2025-10-14T04:36:46",
    "name": "Shubham Jadhav",
    "user_id": "27b0e2c7-9bdf-44a8-b930-8b3eba44d402",
    "event": "Punch In"
  },
  {
    "datetime": "2025-10-14T08:29:45",
    "name": "Shubham Jadhav",
    "user_id": "27b0e2c7-9bdf-44a8-b930-8b3eba44d402",
    "event": "Punch Out"
  },
  {
    "datetime": "2025-10-14T05:01:35",
    "name": "Gaurav Ghadi",
    "user_id": "5d2d7843-9744-4fb5-948b-73cc554a92dc",
    "event": "Punch In"
  },
  {
    "datetime": "2025-10-15T04:59:03",
    "name": "Gaurav Ghadi",
    "user_id": "5d2d7843-9744-4fb5-948b-73cc554a92dc",
    "event": "Punch Out"
  },
  {
    "datetime": "2025-10-14T05:16:41",
    "name": "Shawn Nadar",
    "user_id": "e28c464b-50b3-41ad-8632-3322ce0f5eed",
    "event": "Punch In"
  },
  {
    "datetime": "2025-10-14T14:31:20",
    "name": "Shawn Nadar",
    "user_id": "e28c464b-50b3-41ad-8632-3322ce0f5eed",
    "event": "Punch Out"
  },
  {
    "datetime": "2025-10-14T09:37:50",
    "name": "Shawn Nadar",
    "user_id": "e28c464b-50b3-41ad-8632-3322ce0f5eed",
    "event": "Break Start"
  },
  {
    "datetime": "2025-10-14T10:07:22",
    "name": "Shawn Nadar",
    "user_id": "e28c464b-50b3-41ad-8632-3322ce0f5eed",
    "event": "Break End"
  },
  {
    "datetime": "2025-10-14T13:35:18",
    "name": "Shawn Nadar",
    "user_id": "e28c464b-50b3-41ad-8632-3322ce0f5eed",
    "event": "Break Start"
  },
  {
    "datetime": "2025-10-14T14:05:16",
    "name": "Shawn Nadar",
    "user_id": "e28c464b-50b3-41ad-8632-3322ce0f5eed",
    "event": "Break End"
  },
  {
    "datetime": "2025-10-14T05:26:18",
    "name": "Alizain Patel",
    "user_id": "e634f02e-1486-4ec5-9530-a92c2dc93ef8",
    "event": "Punch In"
  },
  {
    "datetime": "2025-10-14T14:33:24",
    "name": "Alizain Patel",
    "user_id": "e634f02e-1486-4ec5-9530-a92c2dc93ef8",
    "event": "Punch Out"
  },
  {
    "datetime": "2025-10-14T05:28:16",
    "name": "Manesh Chindarkar",
    "user_id": "ba1c916b-8e81-48d9-8ffe-0dfc63cee87f",
    "event": "Punch In"
  },
  {
    "datetime": "2025-10-14T14:35:44",
    "name": "Manesh Chindarkar",
    "user_id": "ba1c916b-8e81-48d9-8ffe-0dfc63cee87f",
    "event": "Punch Out"
  },
  {
    "datetime": "2025-10-14T08:29:24",
    "name": "Manesh Chindarkar",
    "user_id": "ba1c916b-8e81-48d9-8ffe-0dfc63cee87f",
    "event": "Break Start"
  },
  {
    "datetime": "2025-10-14T09:30:00",
    "name": "Manesh Chindarkar",
    "user_id": "ba1c916b-8e81-48d9-8ffe-0dfc63cee87f",
    "event": "Break End"
  },
  {
    "datetime": "2025-10-14T06:00:50",
    "name": "Suhas Kesari",
    "user_id": "53234bff-130a-44e9-b9a0-b1cfdb963c6f",
    "event": "Punch In"
  },
  {
    "datetime": "2025-10-14T17:02:37",
    "name": "Suhas Kesari",
    "user_id": "53234bff-130a-44e9-b9a0-b1cfdb963c6f",
    "event": "Punch Out"
  },
  {
    "datetime": "2025-10-14T09:29:22",
    "name": "Shubham Jadhav",
    "user_id": "27b0e2c7-9bdf-44a8-b930-8b3eba44d402",
    "event": "Punch In"
  },
  {
    "datetime": "2025-10-14T18:34:03",
    "name": "Shubham Jadhav",
    "user_id": "27b0e2c7-9bdf-44a8-b930-8b3eba44d402",
    "event": "Punch Out"
  },
  {
    "datetime": "2025-10-14T11:58:48",
    "name": "Mayur Divekar",
    "user_id": "8b67200f-f49b-47e3-ba26-5f38e2c99501",
    "event": "Punch In"
  },
  {
    "datetime": "2025-10-14T16:16:14",
    "name": "Mayur Divekar",
    "user_id": "8b67200f-f49b-47e3-ba26-5f38e2c99501",
    "event": "Punch Out"
  },
  {
    "datetime": "2025-10-15T04:37:40",
    "name": "Akash Gitaye",
    "user_id": "a53a173f-9a7c-4c4b-875d-7c8edb5b6b7e",
    "event": "Punch In"
  },
  {
    "datetime": "2025-10-15T04:59:19",
    "name": "Gaurav Ghadi",
    "user_id": "5d2d7843-9744-4fb5-948b-73cc554a92dc",
    "event": "Punch In"
  },
  {
    "datetime": "2025-10-15T05:33:37",
    "name": "Manesh Chindarkar",
    "user_id": "ba1c916b-8e81-48d9-8ffe-0dfc63cee87f",
    "event": "Punch In"
  },
  {
    "datetime": "2025-10-15T05:40:13",
    "name": "priti surve",
    "user_id": "f42e59a6-745d-4efd-acc7-95946783d281",
    "event": "Punch In"
  },
  {
    "datetime": "2025-10-15T05:51:26",
    "name": "Alizain Patel",
    "user_id": "e634f02e-1486-4ec5-9530-a92c2dc93ef8",
    "event": "Punch In"
  },
  {
    "datetime": "2025-10-15T05:52:04",
    "name": "Shubham Jadhav",
    "user_id": "27b0e2c7-9bdf-44a8-b930-8b3eba44d402",
    "event": "Punch In"
  },
  {
    "datetime": "2025-10-15T05:59:30",
    "name": "Mayur Divekar",
    "user_id": "8b67200f-f49b-47e3-ba26-5f38e2c99501",
    "event": "Punch In"
  },
  {
    "datetime": "2025-10-15T06:00:10",
    "name": "Suhas Kesari",
    "user_id": "53234bff-130a-44e9-b9a0-b1cfdb963c6f",
    "event": "Punch In"
  }
]
